pyproject.toml
setup.py
./cyberpay_utils/__init__.py
./cyberpay_utils/auth/__init__.py
./cyberpay_utils/auth/client.py
./cyberpay_utils/auth/proto/__init__.py
./cyberpay_utils/auth/proto/auth_service.proto
./cyberpay_utils/auth/proto/auth_service_pb2.py
./cyberpay_utils/auth/proto/auth_service_pb2.pyi
./cyberpay_utils/auth/proto/auth_service_pb2_grpc.py
./cyberpay_utils/billing/__init__.py
./cyberpay_utils/billing/client.py
./cyberpay_utils/billing/proto/__init__.py
./cyberpay_utils/billing/proto/billing.proto
./cyberpay_utils/billing/proto/billing_pb2.py
./cyberpay_utils/billing/proto/billing_pb2.pyi
./cyberpay_utils/billing/proto/billing_pb2_grpc.py
./cyberpay_utils/billing/proto/receipt.proto
./cyberpay_utils/billing/proto/receipt_pb2.py
./cyberpay_utils/billing/proto/receipt_pb2.pyi
./cyberpay_utils/billing/proto/receipt_pb2_grpc.py
./cyberpay_utils/company/__init__.py
./cyberpay_utils/company/client.py
./cyberpay_utils/company/proto/__init__.py
./cyberpay_utils/company/proto/company.proto
./cyberpay_utils/company/proto/company_pb2.py
./cyberpay_utils/company/proto/company_pb2.pyi
./cyberpay_utils/company/proto/company_pb2_grpc.py
./cyberpay_utils/company/proto/company_service.proto
./cyberpay_utils/company/proto/company_service_pb2.py
./cyberpay_utils/company/proto/company_service_pb2.pyi
./cyberpay_utils/company/proto/company_service_pb2_grpc.py
./cyberpay_utils/company/proto/company_user.proto
./cyberpay_utils/company/proto/company_user_pb2.py
./cyberpay_utils/company/proto/company_user_pb2.pyi
./cyberpay_utils/company/proto/company_user_pb2_grpc.py
./cyberpay_utils/email/__init__.py
./cyberpay_utils/email/client.py
./cyberpay_utils/email/proto/__init__.py
./cyberpay_utils/email/proto/email.proto
./cyberpay_utils/email/proto/email_pb2.py
./cyberpay_utils/email/proto/email_pb2.pyi
./cyberpay_utils/email/proto/email_pb2_grpc.py
./cyberpay_utils/general/__init__.py
./cyberpay_utils/general/counters.py
./cyberpay_utils/general/files.py
cyberpay_utils_lib.egg-info/PKG-INFO
cyberpay_utils_lib.egg-info/SOURCES.txt
cyberpay_utils_lib.egg-info/dependency_links.txt
cyberpay_utils_lib.egg-info/not-zip-safe
cyberpay_utils_lib.egg-info/requires.txt
cyberpay_utils_lib.egg-info/top_level.txt