Metadata-Version: 2.1
Name: cyberpay-utils-lib
Version: 0.0.24
Summary: Cyberpay utils library
Author: MADI SPACE
License: MIT
